featherapi/__init__.py
feather_api-1.2.0.dist-info/METADATA
feather_api-1.2.0.dist-info/WHEEL
feather_api-1.2.0.dist-info/top_level.txt
feather_api-1.2.0.dist-info/RECORD
