Metadata-Version: 2.1
Name: feather-api
Version: 1.2.0
Summary: Python wrapper for Feather's API
Home-page: http://github.com/Feather-Official/featherdbtools
Author: Feather Technology Inc.
Author-email: support@try-feather.com
Requires-Dist: setuptools
Requires-Dist: requests
Requires-Dist: pandas
